sortdir/__init__.py
sortdir/cli.py
sortdir/config.py
sortdir/sorting.py
sortdir/utils.py
sortdir-0.2.2.dist-info/entry_points.txt
sortdir-0.2.2.dist-info/LICENSE
sortdir-0.2.2.dist-info/WHEEL
sortdir-0.2.2.dist-info/METADATA
sortdir-0.2.2.dist-info/RECORD
