Metadata-Version: 2.1
Name: sortdir
Version: 0.2.2
Summary: Sorting directory files made easy.
Home-page: https://github.com/yevhenshymotiuk/sortdir
License: MIT
Author: Yevhen Shymotiuk
Author-email: yevhenshymotiuk@gmail.com
Requires-Python: >=3.8,<4.0
Classifier: License :: OSI Approved :: MIT License
Classifier: Programming Language :: Python :: 3
Classifier: Programming Language :: Python :: 3.10
Classifier: Programming Language :: Python :: 3.8
Classifier: Programming Language :: Python :: 3.9
Requires-Dist: colorama (>=0.4.4,<0.5.0)
Requires-Dist: toml (>=0.10.2,<0.11.0)
Requires-Dist: watchdog (>=2.1.2,<3.0.0)
Project-URL: Repository, https://github.com/yevhenshymotiuk/sortdir
